setup.py
tia/__init__.py
tia.egg-info/PKG-INFO
tia.egg-info/SOURCES.txt
tia.egg-info/dependency_links.txt
tia.egg-info/requires.txt
tia.egg-info/top_level.txt
tia/analysis/__init__.py
tia/analysis/pdf_rpts.py
tia/analysis/perf.py
tia/analysis/plots.py
tia/analysis/ta.py
tia/analysis/talib_wrapper.py
tia/analysis/util.py
tia/bbg/__init__.py
tia/bbg/bbg_com.py
tia/bbg/datamgr.py
tia/bbg/example.py
tia/bbg/v3api.py
tia/rlab/__init__.py
tia/rlab/builder.py
tia/rlab/components.py
tia/rlab/font.py
tia/rlab/patch.py
tia/rlab/sample.py
tia/rlab/table.py
tia/tests/__init__.py
tia/tests/test_analysis.py
tia/tests/test_datamgr.py
tia/tests/test_fmt.py
tia/tests/test_rlab_table.py
tia/tests/test_ta.py
tia/util/__init__.py
tia/util/decorator.py
tia/util/fmt.py
tia/util/log.py
tia/util/mplot.py
tia/util/windows.py